martepy/__init__.py
martepy/frameworks/__init__.py
martepy/frameworks/end.json
martepy/frameworks/end_gam.py
martepy/frameworks/simulation_frameworkv2.py
martepy/functions/__init__.py
martepy/functions/bin2csv.py
martepy/functions/extra_functions.py
martepy/functions/gam_functions.py
martepy/marte2/__init__.py
martepy/marte2/config_object.py
martepy/marte2/configwriting.py
martepy/marte2/datasource.py
martepy/marte2/factory.py
martepy/marte2/gam.py
martepy/marte2/generic_application.py
martepy/marte2/qt_classes.py
martepy/marte2/qt_functions.py
martepy/marte2/reader.py
martepy/marte2/serialize.py
martepy/marte2/signal_names_wdw.py
martepy/marte2/sorter.py
martepy/marte2/type_database.py
martepy/marte2/datasources/__init__.py
martepy/marte2/datasources/async_bridge.py
martepy/marte2/datasources/datasources.json
martepy/marte2/datasources/gam_datasource.py
martepy/marte2/datasources/linux_timer.py
martepy/marte2/datasources/logger_datasource.py
martepy/marte2/datasources/timing_datasource.py
martepy/marte2/datasources/epics/__init__.py
martepy/marte2/datasources/epics/publisher.py
martepy/marte2/datasources/epics/subscriber.py
martepy/marte2/datasources/files/__init__.py
martepy/marte2/datasources/files/file_datasources.py
martepy/marte2/datasources/files/reader.py
martepy/marte2/datasources/files/writer.py
martepy/marte2/datasources/sdn/__init__.py
martepy/marte2/datasources/sdn/publisher.py
martepy/marte2/datasources/sdn/subscriber.py
martepy/marte2/datasources/udp/__init__.py
martepy/marte2/datasources/udp/receiver.py
martepy/marte2/datasources/udp/sender.py
martepy/marte2/gams/__init__.py
martepy/marte2/gams/constant_gam.py
martepy/marte2/gams/conversion.py
martepy/marte2/gams/expression_gam.py
martepy/marte2/gams/filter.py
martepy/marte2/gams/gams.json
martepy/marte2/gams/iogam.py
martepy/marte2/gams/message_gam.py
martepy/marte2/gams/mux.py
martepy/marte2/gams/pid.py
martepy/marte2/gams/simulink_gam.py
martepy/marte2/gams/ssm_gam.py
martepy-1.0.4.dist-info/licenses/LICENSE
martepy-1.0.4.dist-info/METADATA
martepy-1.0.4.dist-info/WHEEL
martepy-1.0.4.dist-info/top_level.txt
martepy-1.0.4.dist-info/RECORD
