Metadata-Version: 2.4
Name: martepy
Version: 1.0.4
Summary: This repository provides python classes which represent MARTe2 GAMs, DataSources and applications. Alongside this it provides useful frameworks for debugging and developing applications with MARTe2.
Author-email: Edward Jones <edward.jones1@ukaea.uk>
Project-URL: Homepage, https://github.com/ukaea/MARTe2-python
Classifier: Programming Language :: Python :: 3
Requires-Python: >=3
License-File: LICENSE
Requires-Dist: numpy
Requires-Dist: pyqt5
Requires-Dist: qtpy
Requires-Dist: nodeeditor
Dynamic: license-file
